ck/__init__.py
ck/ck.py
CrypticKey-1.0.dist-info/METADATA
CrypticKey-1.0.dist-info/WHEEL
CrypticKey-1.0.dist-info/top_level.txt
CrypticKey-1.0.dist-info/RECORD
